igusD1/MotorHor.py
igusD1/__init__.py
igusD1/initialisierung.py
igusD1/motorVert.py
igusTest/MotorHor.py
igusTest/__init__.py
igusTest/initialisierung.py
igusTest/motorVert.py
IgusD1-0.0.2.dist-info/LICENSE
IgusD1-0.0.2.dist-info/METADATA
IgusD1-0.0.2.dist-info/WHEEL
IgusD1-0.0.2.dist-info/top_level.txt
IgusD1-0.0.2.dist-info/RECORD
