Metadata-Version: 2.1
Name: IgusD1
Version: 0.0.2
Summary: Package for Ingus D1 
Author: Niklas Kuehnl
Author-email: <niklas.kuehnl@beurer.de>
Keywords: python,first package
Classifier: Development Status :: 3 - Alpha
Classifier: Intended Audience :: Education
Classifier: Programming Language :: Python :: 2
Classifier: Programming Language :: Python :: 3
Classifier: Operating System :: MacOS :: MacOS X
Classifier: Operating System :: Microsoft :: Windows
License-File: LICENSE
